sustaingym/__init__.py
sustaingym/algorithms/__init__.py
sustaingym/algorithms/base.py
sustaingym/algorithms/building/__init__.py
sustaingym/algorithms/building/mpc_controller.py
sustaingym/algorithms/evcharging/__init__.py
sustaingym/algorithms/evcharging/baselines.py
sustaingym/data/__init__.py
sustaingym/data/load_moer.py
sustaingym/data/utils.py
sustaingym/data/building/ASHRAE901_ApartmentHighRise_STD2019_Tucson.table.htm
sustaingym/data/building/ASHRAE901_ApartmentMidRise_STD2019_Tucson.table.htm
sustaingym/data/building/ASHRAE901_Hospital_STD2019_Tucson.table.htm
sustaingym/data/building/ASHRAE901_HotelLarge_STD2019_Tucson.table.htm
sustaingym/data/building/ASHRAE901_HotelSmall_STD2019_Tucson.table.htm
sustaingym/data/building/ASHRAE901_OfficeLarge_STD2019_Tucson.table.htm
sustaingym/data/building/ASHRAE901_OfficeMedium_STD2019_Tucson.table.htm
sustaingym/data/building/ASHRAE901_OfficeSmall_STD2019_Tucson.table.htm
sustaingym/data/building/ASHRAE901_OutPatientHealthCare_STD2019_Tucson.table.htm
sustaingym/data/building/ASHRAE901_RestaurantFastFood_STD2019_Tucson.table.htm
sustaingym/data/building/ASHRAE901_RestaurantSitDown_STD2019_Tucson.table.htm
sustaingym/data/building/ASHRAE901_RetailStandalone_STD2019_Tucson.table.htm
sustaingym/data/building/ASHRAE901_RetailStripmall_STD2019_Tucson.table.htm
sustaingym/data/building/ASHRAE901_SchoolPrimary_STD2019_Tucson.table.htm
sustaingym/data/building/ASHRAE901_SchoolSecondary_STD2019_Tucson.table.htm
sustaingym/data/building/ASHRAE901_Warehouse_STD2019_Tucson.table.htm
sustaingym/data/building/Exercise2A-mytest.csv
sustaingym/data/building/USA_AK_Fairbanks.Intl.AP.702610_TMY3.epw
sustaingym/data/building/USA_AZ_Tucson-Davis-Monthan.AFB.722745_TMY3.epw
sustaingym/data/building/USA_CA_San.Deigo-Brown.Field.Muni.AP.722904_TMY3.epw
sustaingym/data/building/USA_CO_Denver-Aurora-Buckley.AFB.724695_TMY3.epw
sustaingym/data/building/USA_FL_Tampa-MacDill.AFB.747880_TMY3.epw
sustaingym-0.1.7.dist-info/LICENSE
sustaingym-0.1.7.dist-info/METADATA
sustaingym-0.1.7.dist-info/WHEEL
sustaingym-0.1.7.dist-info/top_level.txt
sustaingym-0.1.7.dist-info/RECORD
