Metadata-Version: 2.1
Name: sustaingym
Version: 0.1.7
Summary: SustainGym: Reinforcement Learning Environments for Sustainable Energy Systems
Author-email: Christopher Yeh <cyeh@caltech.edu>
License: CC BY 4.0
Project-URL: Homepage, https://chrisyeh96.github.io/sustaingym/
Project-URL: Repository, https://github.com/chrisyeh96/sustaingym
Project-URL: Bug Tracker, https://github.com/chrisyeh96/sustaingym/issues
Classifier: Programming Language :: Python :: 3
Classifier: Operating System :: OS Independent
Requires-Python: >=3.9
License-File: LICENSE
Requires-Dist: pettingzoo ==1.24.*
Requires-Dist: gymnasium ==0.28.*
Requires-Dist: numpy >=1.23
Provides-Extra: all
Requires-Dist: acnportal >=0.3.3 ; extra == 'all'
Requires-Dist: cvxpy <2,>=1.3 ; extra == 'all'
Requires-Dist: mosek <11,>=10.0.44 ; extra == 'all'
Requires-Dist: openpyxl >=3.1 ; extra == 'all'
Requires-Dist: onnxruntime <2,>=1.15 ; extra == 'all'
Requires-Dist: pandas <3,>=1.1 ; extra == 'all'
Requires-Dist: pvlib >=0.10 ; extra == 'all'
Requires-Dist: pytz ; extra == 'all'
Requires-Dist: requests >=2.31.0 ; extra == 'all'
Requires-Dist: scikit-learn >=1.1.1 ; extra == 'all'
Requires-Dist: scipy >=1.0 ; extra == 'all'
Requires-Dist: xlrd >=2 ; extra == 'all'
Provides-Extra: building
Requires-Dist: cvxpy <2,>=1.3 ; extra == 'building'
Requires-Dist: pvlib >=0.10 ; extra == 'building'
Requires-Dist: scikit-learn >=1.1.1 ; extra == 'building'
Requires-Dist: scipy >=1.0 ; extra == 'building'
Provides-Extra: cogen
Requires-Dist: onnxruntime <2,>=1.15 ; extra == 'cogen'
Requires-Dist: openpyxl >=3.1 ; extra == 'cogen'
Requires-Dist: pandas <3,>=1.1 ; extra == 'cogen'
Requires-Dist: xlrd >=2 ; extra == 'cogen'
Provides-Extra: evcharging
Requires-Dist: acnportal >=0.3.3 ; extra == 'evcharging'
Requires-Dist: cvxpy <2,>=1.3 ; extra == 'evcharging'
Requires-Dist: mosek <11,>=10.0.44 ; extra == 'evcharging'
Requires-Dist: pandas <3,>=1.1 ; extra == 'evcharging'
Requires-Dist: pytz ; extra == 'evcharging'
Requires-Dist: requests >=2.31.0 ; extra == 'evcharging'
Requires-Dist: scikit-learn >=1.1.1 ; extra == 'evcharging'
